setup.py
scripts/scr
simple_container_runtime/__init__.py
simple_container_runtime/api.py
simple_container_runtime/cli.py
simple_container_runtime/docker.py
simple_container_runtime/exceptions.py
simple_container_runtime/file_reader.py
simple_container_runtime/runnable.py
simple_container_runtime/util.py
simple_container_runtime.egg-info/PKG-INFO
simple_container_runtime.egg-info/SOURCES.txt
simple_container_runtime.egg-info/dependency_links.txt
simple_container_runtime.egg-info/entry_points.txt
simple_container_runtime.egg-info/namespace_packages.txt
simple_container_runtime.egg-info/requires.txt
simple_container_runtime.egg-info/top_level.txt
simple_container_runtime.egg-info/zip-safe
simple_container_runtime/aws/__init__.py
simple_container_runtime/aws/s3.py
simple_container_runtime/modules/AwsCfnSignal.py
simple_container_runtime/modules/AwsEcrLogin.py
simple_container_runtime/modules/AwsElbHealthCheck.py
simple_container_runtime/modules/LocalHttpHealthCheck.py
simple_container_runtime/modules/Module.py
simple_container_runtime/modules/__init__.py