Metadata-Version: 1.1
Name: simple-container-runtime
Version: 0.0.3
Summary: Simple-Container-Runtime - simply run docker containers
Home-page: https://github.com/cfn-sphere/simple-container-runtime
Author: Marco Hoyer
Author-email: marco_hoyer@gmx.de
License: APACHE LICENSE, VERSION 2.0
Platform: UNKNOWN
Classifier: Development Status :: 3 - Alpha
Classifier: Programming Language :: Python
